age_calculator_lib/__init__.py
age_calculator_lib/__main__.py
age_calculator_lib/core.py
agecalculatorlib-0.1.0.dist-info/licenses/LICENSE
agecalculatorlib-0.1.0.dist-info/METADATA
agecalculatorlib-0.1.0.dist-info/WHEEL
agecalculatorlib-0.1.0.dist-info/entry_points.txt
agecalculatorlib-0.1.0.dist-info/top_level.txt
agecalculatorlib-0.1.0.dist-info/RECORD
