Metadata-Version: 2.4
Name: AgeCalculatorLib
Version: 0.1.0
Summary: Calculate age from birth date
Author: Asmaa Senan
Author-email: Asmaa Senan <asmaasenan3@gmail.com>
License: MIT License
Requires-Python: >=3.7
License-File: LICENSE
Dynamic: author
Dynamic: license-file
Dynamic: requires-python
